nserver/__init__.py
nserver/__main__.py
nserver/_version.py
nserver/application.py
nserver/cli.py
nserver/exceptions.py
nserver/middleware.py
nserver/models.py
nserver/py.typed
nserver/records.py
nserver/rules.py
nserver/server.py
nserver/transport.py
nserver/util.py
nserver-3.0.1.dist-info/licenses/LICENCE
nserver-3.0.1.dist-info/licenses/NOTICE
nserver-3.0.1.dist-info/METADATA
nserver-3.0.1.dist-info/WHEEL
nserver-3.0.1.dist-info/entry_points.txt
nserver-3.0.1.dist-info/top_level.txt
nserver-3.0.1.dist-info/RECORD
