Metadata-Version: 2.4
Name: nserver
Version: 3.0.1
Summary: DNS Name Server Framework
Author-email: Nicholas Hairs <info+nserver@nicholashairs.com>
License: MIT
Project-URL: HomePage, https://nhairs.github.io/nserver
Project-URL: GitHub, https://github.com/nhairs/nserver
Classifier: Development Status :: 4 - Beta
Classifier: Programming Language :: Python :: 3 :: Only
Classifier: Programming Language :: Python :: 3.8
Classifier: Programming Language :: Python :: 3.9
Classifier: Programming Language :: Python :: 3.10
Classifier: Programming Language :: Python :: 3.11
Classifier: Programming Language :: Python :: 3.12
Classifier: Programming Language :: Python :: 3.13
Classifier: License :: OSI Approved :: MIT License
Classifier: Typing :: Typed
Classifier: Topic :: Internet
Classifier: Topic :: Internet :: Name Service (DNS)
Requires-Python: >=3.8
License-File: LICENCE
License-File: NOTICE
Requires-Dist: dnslib
Requires-Dist: pillar~=0.3
Requires-Dist: tldextract
Requires-Dist: typing-extensions; python_version < "3.10"
Provides-Extra: dev
Requires-Dist: tox; extra == "dev"
Requires-Dist: tox-uv; extra == "dev"
Requires-Dist: validate-pyproject[all]; extra == "dev"
Requires-Dist: black; extra == "dev"
Requires-Dist: pylint; extra == "dev"
Requires-Dist: mypy; extra == "dev"
Requires-Dist: pytest; extra == "dev"
Requires-Dist: setuptools; extra == "dev"
Requires-Dist: wheel; extra == "dev"
Requires-Dist: black; extra == "dev"
Requires-Dist: mkdocs; extra == "dev"
Requires-Dist: mkdocs-material>=8.5; extra == "dev"
Requires-Dist: mkdocs-awesome-pages-plugin; extra == "dev"
Requires-Dist: mdx_truly_sane_lists; extra == "dev"
Requires-Dist: mkdocstrings[python]; extra == "dev"
Requires-Dist: mkdocs-gen-files; extra == "dev"
Requires-Dist: mkdocs-literate-nav; extra == "dev"
Requires-Dist: mike; extra == "dev"
Dynamic: license-file
